onprem/__init__.py
onprem/_modidx.py
onprem/utils.py
onprem/app/OnPrem.py
onprem/app/__init__.py
onprem/app/console.py
onprem/app/utils.py
onprem/app/pages/1_Prompts.py
onprem/app/pages/2_Document_QA.py
onprem/app/pages/3_Document_Search.py
onprem/app/pages/4_Document_Analysis.py
onprem/app/pages/5_Workflow_Builder.py
onprem/app/pages/6_Manage.py
onprem/app/pages/__init__.py
onprem/hf/__init__.py
onprem/hf/base.py
onprem/hf/tensors.py
onprem/hf/data/__init__.py
onprem/hf/data/base.py
onprem/hf/data/labels.py
onprem/hf/data/questions.py
onprem/hf/data/sequences.py
onprem/hf/data/texts.py
onprem/hf/data/tokens.py
onprem/hf/models/__init__.py
onprem/hf/models/models.py
onprem/hf/models/onnx.py
onprem/hf/models/registry.py
onprem/hf/models/tokendetection.py
onprem/hf/models/pooling/__init__.py
onprem/hf/models/pooling/base.py
onprem/hf/models/pooling/cls.py
onprem/hf/models/pooling/factory.py
onprem/hf/models/pooling/mean.py
onprem/hf/train/__init__.py
onprem/hf/train/hfonnx.py
onprem/hf/train/hftrainer.py
onprem/hf/train/mlonnx.py
onprem/ingest/__init__.py
onprem/ingest/base.py
onprem/ingest/helpers.py
onprem/ingest/pdftables.py
onprem/ingest/stores/__init__.py
onprem/ingest/stores/base.py
onprem/ingest/stores/dense.py
onprem/ingest/stores/dual.py
onprem/ingest/stores/factory.py
onprem/ingest/stores/sparse.py
onprem/llm/__init__.py
onprem/llm/backends.py
onprem/llm/base.py
onprem/llm/helpers.py
onprem/pipelines/__init__.py
onprem/pipelines/classifier.py
onprem/pipelines/extractor.py
onprem/pipelines/guider.py
onprem/pipelines/summarizer.py
onprem/pipelines/agent/__init__.py
onprem/pipelines/agent/base.py
onprem/pipelines/agent/model.py
onprem/pipelines/agent/tools.py
onprem/sk/__init__.py
onprem/sk/base.py
onprem/sk/clf.py
onprem/sk/tm.py
onprem/workflow/__init__.py
onprem/workflow/__main__.py
onprem/workflow/base.py
onprem/workflow/cli.py
onprem/workflow/convenience.py
onprem/workflow/document_transformers.py
onprem/workflow/engine.py
onprem/workflow/exceptions.py
onprem-0.20.0.dist-info/licenses/LICENSE
onprem-0.20.0.dist-info/METADATA
onprem-0.20.0.dist-info/WHEEL
onprem-0.20.0.dist-info/entry_points.txt
onprem-0.20.0.dist-info/top_level.txt
onprem-0.20.0.dist-info/RECORD
