Metadata-Version: 2.4
Name: onprem
Version: 0.20.0
Summary: A tool for running on-premises large language models on non-public data
Home-page: https://github.com/amaiya/onprem
Author: Arun S. Maiya
Author-email: arun@maiya.net
License: Apache Software License 2.0
Keywords: nbdev jupyter notebook python
Classifier: Development Status :: 4 - Beta
Classifier: Intended Audience :: Developers
Classifier: Natural Language :: English
Classifier: Programming Language :: Python :: 3.10
Classifier: License :: OSI Approved :: Apache Software License
Requires-Python: >=3.10
License-File: LICENSE
Requires-Dist: unstructured[all-docs]
Requires-Dist: nltk>=3.9.1
Requires-Dist: PyMuPDF
Requires-Dist: pymupdf4llm==0.0.17
Requires-Dist: extract-msg
Requires-Dist: tabulate
Requires-Dist: pandoc
Requires-Dist: pypandoc
Requires-Dist: requests
Requires-Dist: tqdm
Requires-Dist: syntok
Requires-Dist: pandas
Requires-Dist: sentence_transformers
Requires-Dist: cmake
Requires-Dist: setfit
Requires-Dist: guidance>=0.1.5
Requires-Dist: langchain>=0.3.18
Requires-Dist: langchain-community>=0.3.18
Requires-Dist: langchain_litellm==0.1.4
Requires-Dist: litellm
Requires-Dist: langchain-openai
Requires-Dist: langchain-huggingface
Requires-Dist: huggingface_hub
Requires-Dist: transformers
Requires-Dist: accelerate
Requires-Dist: langdetect
Requires-Dist: charset_normalizer
Requires-Dist: python-magic
Requires-Dist: whoosh-reloaded
Requires-Dist: pyparsing
Requires-Dist: openpyxl
Requires-Dist: streamlit
Requires-Dist: smolagents
Requires-Dist: markdownify
Requires-Dist: mcpadapt
Requires-Dist: gmft
Requires-Dist: datasets==3.6.0
Provides-Extra: dev
Requires-Dist: nbdev; extra == "dev"
Provides-Extra: chroma
Requires-Dist: chromadb; extra == "chroma"
Requires-Dist: langchain_chroma; extra == "chroma"
Provides-Extra: explain
Requires-Dist: shap; extra == "explain"
Dynamic: author
Dynamic: author-email
Dynamic: classifier
Dynamic: description
Dynamic: description-content-type
Dynamic: home-page
Dynamic: keywords
Dynamic: license
Dynamic: license-file
Dynamic: provides-extra
Dynamic: requires-dist
Dynamic: requires-python
Dynamic: summary
